checkerboard/__init__.py
checkerboard/checkerboard.py
checkerboard/utils.py
checkerboard/_tests/__init__.py
checkerboard/_tests/test_dock_widget.py
napari_checkerboard-0.0.3.dist-info/LICENSE
napari_checkerboard-0.0.3.dist-info/METADATA
napari_checkerboard-0.0.3.dist-info/WHEEL
napari_checkerboard-0.0.3.dist-info/entry_points.txt
napari_checkerboard-0.0.3.dist-info/top_level.txt
napari_checkerboard-0.0.3.dist-info/RECORD
