Metadata-Version: 2.1
Name: napari-checkerboard
Version: 0.0.3
Summary: Compare two images with the itk checkerboard filter
Home-page: https://github.com/ViktorvdValk/napari-checkerboard
Author: Viktor van der Valk
Author-email: v.o.van_der_valk@lumc.nl
License: Apache Software License 2.0
Platform: UNKNOWN
Classifier: Development Status :: 4 - Beta
Classifier: Intended Audience :: Developers
Classifier: Framework :: napari
Classifier: Topic :: Software Development :: Testing
Classifier: Programming Language :: Python
Classifier: Programming Language :: Python :: 3
Classifier: Programming Language :: Python :: 3.7
Classifier: Programming Language :: Python :: 3.8
Classifier: Programming Language :: Python :: 3.9
Classifier: Operating System :: OS Independent
Classifier: License :: OSI Approved :: Apache Software License
Requires-Python: >=3.6
License-File: LICENSE
Requires-Dist: napari-plugin-engine (>=0.1.4)
Requires-Dist: numpy (>=1.19.0)
Requires-Dist: napari (>=0.4.6)
Requires-Dist: magicgui (>=0.2.6)
Requires-Dist: itk-elastix (>=0.11.1)
Requires-Dist: itk-napari-conversion (>=0.3.1)
Requires-Dist: napari-itk-io (>=0.1.0)
